coding_assistant/__init__.py
coding_assistant/callbacks.py
coding_assistant/config.py
coding_assistant/default_instructions.md
coding_assistant/history.py
coding_assistant/instructions.py
coding_assistant/main.py
coding_assistant/paths.py
coding_assistant/sandbox.py
coding_assistant/trace.py
coding_assistant/ui.py
coding_assistant/framework/__init__.py
coding_assistant/framework/agent.py
coding_assistant/framework/builtin_tools.py
coding_assistant/framework/callbacks.py
coding_assistant/framework/chat.py
coding_assistant/framework/execution.py
coding_assistant/framework/history.py
coding_assistant/framework/interrupts.py
coding_assistant/framework/parameters.py
coding_assistant/framework/results.py
coding_assistant/framework/types.py
coding_assistant/framework/tests/.gitignore
coding_assistant/framework/tests/helpers.py
coding_assistant/framework/tests/test_agents.py
coding_assistant/framework/tests/test_callbacks_integration.py
coding_assistant/framework/tests/test_chat_loop_interrupts.py
coding_assistant/framework/tests/test_chat_mode.py
coding_assistant/framework/tests/test_execution.py
coding_assistant/framework/tests/test_execution_compact_conversation.py
coding_assistant/framework/tests/test_interrupts.py
coding_assistant/framework/tests/test_model_contract.py
coding_assistant/framework/tests/test_parameters.py
coding_assistant/framework/tests/test_run_loop_slices.py
coding_assistant/framework/tests/test_vision.py
coding_assistant/llm/adapters.py
coding_assistant/llm/openai.py
coding_assistant/llm/test_openai.py
coding_assistant/llm/types.py
coding_assistant/mcp/__init__.py
coding_assistant/mcp/__main__.py
coding_assistant/mcp/filesystem.py
coding_assistant/mcp/main.py
coding_assistant/mcp/proc.py
coding_assistant/mcp/python.py
coding_assistant/mcp/shell.py
coding_assistant/mcp/skills.py
coding_assistant/mcp/tasks.py
coding_assistant/mcp/todo.py
coding_assistant/mcp/utils.py
coding_assistant/mcp/tests/__init__.py
coding_assistant/mcp/tests/test_filesystem.py
coding_assistant_cli-0.1.8.dist-info/METADATA
coding_assistant_cli-0.1.8.dist-info/WHEEL
coding_assistant_cli-0.1.8.dist-info/entry_points.txt
coding_assistant_cli-0.1.8.dist-info/licenses/LICENSE
coding_assistant_cli-0.1.8.dist-info/RECORD
