Metadata-Version: 2.4
Name: coding-assistant-cli
Version: 0.1.8
Summary: An agent-orchestrated CLI for streamlining and automating coding tasks.
License-Expression: MIT
License-File: LICENSE
Requires-Python: >=3.12
Requires-Dist: aiofiles
Requires-Dist: dacite>=1.9.2
Requires-Dist: debugpy
Requires-Dist: fastmcp
Requires-Dist: httpx-sse>=0.4.3
Requires-Dist: httpx>=0.28.1
Requires-Dist: json5>=0.12.1
Requires-Dist: landlock
Requires-Dist: prompt-toolkit
Requires-Dist: pydantic
Requires-Dist: python-frontmatter>=1.1.0
Requires-Dist: requests
Requires-Dist: rich
